{ "backgroundcolor":"#000000",
 "height":150,
 "layers":[
        {
         "compression":"zlib",
         "data":"eJzt2WFyojAYgGGO6AH84VE8ASfpsTxInVamSEUIBPMRHmee2e7uBEheQ1u8Nc31BgAAAAAAAAAAAAAAAAAAAAAAAAAAAMzy1TRNDue709+fl3Om40YwNrc2w7Hndjo\/zp\/DcC41eTW3NsNxP7Gf2oH+XIb\/V3pPrJ3fVnP7xH5K6VR6P6yd31ZzS+00PPc7azqlnCfSuNxz00knnXTSSaeIc9Op7k5L6PQ8Zolov+dGWe8tOkX\/PXeoe6ZS6XOjp7ml9h\/zif3EevbTtvspl3dtmt4r533\/qN+f1pxPp3106r900kknnSKN00mnkp1Oj7\/3XHauuk41q6RT6ff8R5ToVPr9uVdLXlPHeNep9POto5vbqfT78ujmdmpnHGtMru9rex+3Zv3WdEqdW7R1KzFuSU+ddNKpXKfhzyA6bbMGr9Y5pZP9lD5uyXqVuu+ljIm63jrtY7112sd667SP9Y7eqftap310Go4d8+58JQx\/xi19PUtNdepe0d6nc8dN3QOiXOcUnWJc55pOt99\/+3G\/Z1wfin8Wc0Qv2vzr1PUvfY8+qm7tUzpFvS\/Uet\/TKdZ1Hr3T1DP+KNd59E72U4x56KRThPnpFOs6ddIpwjx00inC\/BI7Xds\/oeZRe6f+uIlnfEmfP02p5fOgOXPLOb85jQAAAAAAAAAAAAAAAAAAAAAAjuwb6pdBGg==",
         "encoding":"base64",
         "height":150,
         "name":"back",
         "opacity":0.5,
         "type":"tilelayer",
         "visible":true,
         "width":106,
         "x":0,
         "y":0
        }, 
        {
         "compression":"zlib",
         "data":"eJzt3N1xozAUBlDK2Mr2ycWkAmpzC+5k17OGISw\/AknADefM3MkDtoT4kENuMmkaAAAAAAAAAAAAAAAAAAAAAAAAAAAAYEnbNF+PgvUerxv7VXGeM+qotQ3nGc\/R5lfz+Ddeb7SW\/niBuY6ulLV9lVhbSk6Z90ByTtFsySl3H8lpv5vlNHsOVzd17oFzWlvLT86p2jU8Yg45yelIcopBTjHIKQY5xXCRnJpH0\/dzcip5LW2QvIbnunVte2stp1LVDsZe6lVGyWnunE\/ow5baT33NrWVcOdfwCEvnvLa2Cvup2v39Wn9JWDXWNtwzE8fktIOcYpBTDHKKQU4xyCmGE3KaPZbrdUBdce69Plms\/pzLuVJzetfz72uGtacf8ay+out4r3VP3+H5ee9zNEZKf2\/pc3FPf+8utvb3lvpCKd+f5o4nVpj+ammja5i0nybG6PZT1ecIORW5htWf9+78PFLqHj0oJ\/spf5zqv9eQU\/XPvW\/Xd\/xcvmEOOW14z\/i5fG0c+ynfGfuJ88gpBjnFIKcY5BRDak4benn\/9fbOrLnec8Bazanr1e6son8PWrD3HK0Wc2q\/fw23n2bWFLH6HMa6z4pfg+JYw2s\/7E9M+T0ojrXl2svpPHKK4S45TfWeI7lLTtHJKQY5xSCnGOQUw0\/P6dNznaxIz325OV25j7SUUbSstuQ01d+7ak4pGUXKKqW3mtEjn+2Zd2OP\/+djsJrsaW9YW1bvfCEyAAAAAAAAAAAAAAAAAAAAAIDb+gPLjmrg",
         "encoding":"base64",
         "height":150,
         "name":"front",
         "opacity":1,
         "type":"tilelayer",
         "visible":true,
         "width":106,
         "x":0,
         "y":0
        }, 
        {
         "color":"#5555ff",
         "draworder":"topdown",
         "height":0,
         "name":"mods",
         "objects":[],
         "opacity":1,
         "type":"objectgroup",
         "visible":true,
         "width":0,
         "x":0,
         "y":0
        }, 
        {
         "color":"#ff0000",
         "draworder":"topdown",
         "height":0,
         "name":"objects",
         "objects":[
                {
                 "gid":7904,
                 "height":18,
                 "id":908,
                 "name":"",
                 "properties":
                    {

                    },
                 "rotation":0,
                 "type":"",
                 "visible":true,
                 "width":24,
                 "x":624,
                 "y":864
                }, 
                {
                 "gid":7904,
                 "height":18,
                 "id":909,
                 "name":"",
                 "properties":
                    {

                    },
                 "rotation":0,
                 "type":"",
                 "visible":true,
                 "width":24,
                 "x":184,
                 "y":864
                }, 
                {
                 "gid":5952,
                 "height":8,
                 "id":910,
                 "name":"",
                 "properties":
                    {

                    },
                 "rotation":0,
                 "type":"",
                 "visible":true,
                 "width":16,
                 "x":240,
                 "y":760
                }, 
                {
                 "gid":5952,
                 "height":8,
                 "id":911,
                 "name":"",
                 "properties":
                    {

                    },
                 "rotation":0,
                 "type":"",
                 "visible":true,
                 "width":16,
                 "x":464,
                 "y":760
                }, 
                {
                 "gid":5952,
                 "height":8,
                 "id":912,
                 "name":"",
                 "properties":
                    {

                    },
                 "rotation":0,
                 "type":"",
                 "visible":true,
                 "width":16,
                 "x":352,
                 "y":760
                }, 
                {
                 "gid":5952,
                 "height":8,
                 "id":913,
                 "name":"",
                 "properties":
                    {

                    },
                 "rotation":0,
                 "type":"",
                 "visible":true,
                 "width":16,
                 "x":688,
                 "y":760
                }, 
                {
                 "gid":5952,
                 "height":8,
                 "id":914,
                 "name":"",
                 "properties":
                    {

                    },
                 "rotation":0,
                 "type":"",
                 "visible":true,
                 "width":16,
                 "x":576,
                 "y":760
                }, 
                {
                 "gid":5952,
                 "height":8,
                 "id":915,
                 "name":"",
                 "properties":
                    {

                    },
                 "rotation":0,
                 "type":"",
                 "visible":true,
                 "width":16,
                 "x":128,
                 "y":760
                }, 
                {
                 "gid":7904,
                 "height":18,
                 "id":923,
                 "name":"",
                 "properties":
                    {

                    },
                 "rotation":0,
                 "type":"",
                 "visible":true,
                 "width":24,
                 "x":424,
                 "y":616
                }, 
                {
                 "gid":7904,
                 "height":18,
                 "id":924,
                 "name":"",
                 "properties":
                    {

                    },
                 "rotation":0,
                 "type":"",
                 "visible":true,
                 "width":24,
                 "x":384,
                 "y":616
                }, 
                {
                 "gid":5952,
                 "height":8,
                 "id":927,
                 "name":"",
                 "properties":
                    {

                    },
                 "rotation":0,
                 "type":"",
                 "visible":true,
                 "width":16,
                 "x":352,
                 "y":632
                }, 
                {
                 "gid":5952,
                 "height":8,
                 "id":928,
                 "name":"",
                 "properties":
                    {

                    },
                 "rotation":0,
                 "type":"",
                 "visible":true,
                 "width":16,
                 "x":240,
                 "y":632
                }, 
                {
                 "gid":5952,
                 "height":8,
                 "id":929,
                 "name":"",
                 "properties":
                    {

                    },
                 "rotation":0,
                 "type":"",
                 "visible":true,
                 "width":16,
                 "x":464,
                 "y":632
                }, 
                {
                 "gid":5952,
                 "height":8,
                 "id":930,
                 "name":"",
                 "properties":
                    {

                    },
                 "rotation":0,
                 "type":"",
                 "visible":true,
                 "width":16,
                 "x":104,
                 "y":648
                }, 
                {
                 "gid":5952,
                 "height":8,
                 "id":931,
                 "name":"",
                 "properties":
                    {

                    },
                 "rotation":0,
                 "type":"",
                 "visible":true,
                 "width":16,
                 "x":576,
                 "y":632
                }, 
                {
                 "gid":239,
                 "height":8,
                 "id":932,
                 "name":"",
                 "properties":
                    {

                    },
                 "rotation":0,
                 "type":"",
                 "visible":true,
                 "width":8,
                 "x":8,
                 "y":424
                }, 
                {
                 "gid":5952,
                 "height":8,
                 "id":933,
                 "name":"",
                 "properties":
                    {

                    },
                 "rotation":0,
                 "type":"",
                 "visible":true,
                 "width":16,
                 "x":464,
                 "y":536
                }, 
                {
                 "gid":5952,
                 "height":8,
                 "id":934,
                 "name":"",
                 "properties":
                    {

                    },
                 "rotation":0,
                 "type":"",
                 "visible":true,
                 "width":16,
                 "x":352,
                 "y":536
                }, 
                {
                 "height":8,
                 "id":935,
                 "name":"",
                 "properties":
                    {
                     "npc":"apex",
                     "typeName":"labscientist"
                    },
                 "rotation":0,
                 "type":"",
                 "visible":true,
                 "width":8,
                 "x":264,
                 "y":688
                }, 
                {
                 "gid":2128,
                 "height":64,
                 "id":941,
                 "name":"",
                 "properties":
                    {

                    },
                 "rotation":0,
                 "type":"",
                 "visible":true,
                 "width":32,
                 "x":680,
                 "y":616
                }, 
                {
                 "gid":6995,
                 "height":8,
                 "id":942,
                 "name":"",
                 "properties":
                    {

                    },
                 "rotation":0,
                 "type":"",
                 "visible":true,
                 "width":8,
                 "x":672,
                 "y":712
                }, 
                {
                 "gid":6995,
                 "height":8,
                 "id":943,
                 "name":"",
                 "properties":
                    {

                    },
                 "rotation":0,
                 "type":"",
                 "visible":true,
                 "width":8,
                 "x":656,
                 "y":712
                }, 
                {
                 "gid":5090,
                 "height":40,
                 "id":945,
                 "name":"",
                 "properties":
                    {

                    },
                 "rotation":0,
                 "type":"",
                 "visible":true,
                 "width":8,
                 "x":664,
                 "y":728
                }, 
                {
                 "gid":6995,
                 "height":8,
                 "id":949,
                 "name":"",
                 "properties":
                    {

                    },
                 "rotation":0,
                 "type":"",
                 "visible":true,
                 "width":8,
                 "x":152,
                 "y":712
                }, 
                {
                 "gid":6995,
                 "height":8,
                 "id":950,
                 "name":"",
                 "properties":
                    {

                    },
                 "rotation":0,
                 "type":"",
                 "visible":true,
                 "width":8,
                 "x":168,
                 "y":712
                }, 
                {
                 "gid":5090,
                 "height":40,
                 "id":951,
                 "name":"",
                 "properties":
                    {

                    },
                 "rotation":0,
                 "type":"",
                 "visible":true,
                 "width":8,
                 "x":160,
                 "y":728
                }, 
                {
                 "gid":5952,
                 "height":8,
                 "id":954,
                 "name":"",
                 "properties":
                    {

                    },
                 "rotation":0,
                 "type":"",
                 "visible":true,
                 "width":16,
                 "x":712,
                 "y":648
                }, 
                {
                 "gid":2147485841,
                 "height":40,
                 "id":963,
                 "name":"",
                 "properties":
                    {
                     "parameters":"{ \"treasurePools\" : [ \"apexbaseTreasure\" ] }"
                    },
                 "rotation":0,
                 "type":"",
                 "visible":true,
                 "width":32,
                 "x":728,
                 "y":728
                }, 
                {
                 "gid":2147485841,
                 "height":40,
                 "id":964,
                 "name":"",
                 "properties":
                    {
                     "parameters":"{ \"treasurePools\" : [ \"apexbaseTreasure\" ] }"
                    },
                 "rotation":0,
                 "type":"",
                 "visible":true,
                 "width":32,
                 "x":688,
                 "y":728
                }, 
                {
                 "gid":2193,
                 "height":40,
                 "id":965,
                 "name":"",
                 "properties":
                    {
                     "parameters":"{ \"treasurePools\" : [ \"apexbaseTreasure\" ] }"
                    },
                 "rotation":0,
                 "type":"",
                 "visible":true,
                 "width":32,
                 "x":112,
                 "y":728
                }, 
                {
                 "gid":2193,
                 "height":40,
                 "id":966,
                 "name":"",
                 "properties":
                    {
                     "parameters":"{ \"treasurePools\" : [ \"apexbaseTreasure\" ] }"
                    },
                 "rotation":0,
                 "type":"",
                 "visible":true,
                 "width":32,
                 "x":72,
                 "y":728
                }, 
                {
                 "gid":2161,
                 "height":16,
                 "id":967,
                 "name":"",
                 "properties":
                    {

                    },
                 "rotation":0,
                 "type":"",
                 "visible":true,
                 "width":42,
                 "x":720,
                 "y":616
                }, 
                {
                 "gid":2147486002,
                 "height":18,
                 "id":968,
                 "name":"",
                 "properties":
                    {

                    },
                 "rotation":0,
                 "type":"",
                 "visible":true,
                 "width":15,
                 "x":768,
                 "y":616
                }, 
                {
                 "gid":2354,
                 "height":18,
                 "id":970,
                 "name":"",
                 "properties":
                    {

                    },
                 "rotation":0,
                 "type":"",
                 "visible":true,
                 "width":15,
                 "x":48,
                 "y":616
                }, 
                {
                 "gid":2147485809,
                 "height":16,
                 "id":971,
                 "name":"",
                 "properties":
                    {

                    },
                 "rotation":0,
                 "type":"",
                 "visible":true,
                 "width":42,
                 "x":72,
                 "y":616
                }, 
                {
                 "gid":1344,
                 "height":24,
                 "id":975,
                 "name":"",
                 "properties":
                    {

                    },
                 "rotation":0,
                 "type":"",
                 "visible":true,
                 "width":16,
                 "x":728,
                 "y":600
                }, 
                {
                 "gid":6319,
                 "height":16,
                 "id":976,
                 "name":"",
                 "properties":
                    {

                    },
                 "rotation":0,
                 "type":"",
                 "visible":true,
                 "width":8,
                 "x":80,
                 "y":600
                }, 
                {
                 "height":8,
                 "id":977,
                 "name":"",
                 "properties":
                    {
                     "monster":"minidrone"
                    },
                 "rotation":0,
                 "type":"",
                 "visible":true,
                 "width":8,
                 "x":408,
                 "y":456
                }, 
                {
                 "gid":2179,
                 "height":48,
                 "id":978,
                 "name":"",
                 "properties":
                    {

                    },
                 "rotation":0,
                 "type":"",
                 "visible":true,
                 "width":48,
                 "x":480,
                 "y":856
                }, 
                {
                 "gid":2346,
                 "height":16,
                 "id":983,
                 "name":"",
                 "properties":
                    {

                    },
                 "rotation":0,
                 "type":"",
                 "visible":true,
                 "width":16,
                 "x":408,
                 "y":752
                }, 
                {
                 "gid":2147485975,
                 "height":24,
                 "id":984,
                 "name":"",
                 "properties":
                    {

                    },
                 "rotation":0,
                 "type":"",
                 "visible":true,
                 "width":24,
                 "x":728,
                 "y":856
                }, 
                {
                 "gid":2338,
                 "height":32,
                 "id":985,
                 "name":"",
                 "properties":
                    {
                     "parameters":"{ \"treasurePools\" : [ \"foodTreasureMedium\" ] }"
                    },
                 "rotation":0,
                 "type":"",
                 "visible":true,
                 "width":24,
                 "x":760,
                 "y":856
                }, 
                {
                 "gid":2147485809,
                 "height":16,
                 "id":986,
                 "name":"",
                 "properties":
                    {

                    },
                 "rotation":0,
                 "type":"",
                 "visible":true,
                 "width":42,
                 "x":664,
                 "y":856
                }, 
                {
                 "gid":2994,
                 "height":8,
                 "id":987,
                 "name":"",
                 "properties":
                    {

                    },
                 "rotation":0,
                 "type":"",
                 "visible":true,
                 "width":16,
                 "x":664,
                 "y":840
                }, 
                {
                 "gid":6309,
                 "height":16,
                 "id":989,
                 "name":"",
                 "properties":
                    {

                    },
                 "rotation":0,
                 "type":"",
                 "visible":true,
                 "width":8,
                 "x":688,
                 "y":840
                }, 
                {
                 "gid":2365,
                 "height":32,
                 "id":991,
                 "name":"",
                 "properties":
                    {

                    },
                 "rotation":0,
                 "type":"",
                 "visible":true,
                 "width":24,
                 "x":96,
                 "y":824
                }, 
                {
                 "gid":2213,
                 "height":16,
                 "id":992,
                 "name":"",
                 "properties":
                    {

                    },
                 "rotation":0,
                 "type":"",
                 "visible":true,
                 "width":16,
                 "x":64,
                 "y":840
                }, 
                {
                 "gid":2139,
                 "height":48,
                 "id":993,
                 "name":"",
                 "properties":
                    {

                    },
                 "rotation":0,
                 "type":"",
                 "visible":true,
                 "width":48,
                 "x":528,
                 "y":856
                }, 
                {
                 "gid":2147485827,
                 "height":48,
                 "id":994,
                 "name":"",
                 "properties":
                    {

                    },
                 "rotation":0,
                 "type":"",
                 "visible":true,
                 "width":48,
                 "x":304,
                 "y":856
                }, 
                {
                 "gid":2147485827,
                 "height":48,
                 "id":995,
                 "name":"",
                 "properties":
                    {

                    },
                 "rotation":0,
                 "type":"",
                 "visible":true,
                 "width":48,
                 "x":256,
                 "y":856
                }, 
                {
                 "gid":5630,
                 "height":8,
                 "id":996,
                 "name":"",
                 "properties":
                    {

                    },
                 "rotation":0,
                 "type":"",
                 "visible":true,
                 "width":16,
                 "x":688,
                 "y":552
                }, 
                {
                 "gid":5630,
                 "height":8,
                 "id":997,
                 "name":"",
                 "properties":
                    {

                    },
                 "rotation":0,
                 "type":"",
                 "visible":true,
                 "width":16,
                 "x":128,
                 "y":552
                }, 
                {
                 "height":8,
                 "id":999,
                 "name":"",
                 "properties":
                    {
                     "npc":"apex",
                     "typeName":"labscientist"
                    },
                 "rotation":0,
                 "type":"",
                 "visible":true,
                 "width":8,
                 "x":768,
                 "y":576
                }, 
                {
                 "gid":2365,
                 "height":32,
                 "id":1000,
                 "name":"",
                 "properties":
                    {

                    },
                 "rotation":0,
                 "type":"",
                 "visible":true,
                 "width":24,
                 "x":504,
                 "y":712
                }, 
                {
                 "gid":2365,
                 "height":32,
                 "id":1001,
                 "name":"",
                 "properties":
                    {

                    },
                 "rotation":0,
                 "type":"",
                 "visible":true,
                 "width":24,
                 "x":536,
                 "y":704
                }, 
                {
                 "gid":2147485735,
                 "height":15,
                 "id":1002,
                 "name":"",
                 "properties":
                    {

                    },
                 "rotation":0,
                 "type":"",
                 "visible":true,
                 "width":16,
                 "x":712,
                 "y":856
                }, 
                {
                 "gid":2147485933,
                 "height":16,
                 "id":1003,
                 "name":"",
                 "properties":
                    {
                     "parameters":"{ \"treasurePools\" : [ \"apexbaseTreasure\" ] }"
                    },
                 "rotation":0,
                 "type":"",
                 "visible":true,
                 "width":40,
                 "x":288,
                 "y":728
                }, 
                {
                 "gid":2354,
                 "height":18,
                 "id":1004,
                 "name":"",
                 "properties":
                    {

                    },
                 "rotation":0,
                 "type":"",
                 "visible":true,
                 "width":15,
                 "x":264,
                 "y":728
                }, 
                {
                 "gid":2147485993,
                 "height":32,
                 "id":1005,
                 "name":"",
                 "properties":
                    {

                    },
                 "rotation":0,
                 "type":"",
                 "visible":true,
                 "width":32,
                 "x":296,
                 "y":712
                }],
         "opacity":1,
         "type":"objectgroup",
         "visible":true,
         "width":0,
         "x":0,
         "y":0
        }, 
        {
         "color":"#ffff00",
         "draworder":"topdown",
         "height":0,
         "name":"wiring - lights & guns",
         "objects":[
                {
                 "height":0,
                 "id":947,
                 "name":"",
                 "polyline":[
                        {
                         "x":0,
                         "y":0
                        }, 
                        {
                         "x":8,
                         "y":-16
                        }, 
                        {
                         "x":16,
                         "y":0
                        }],
                 "properties":
                    {

                    },
                 "rotation":0,
                 "type":"",
                 "visible":true,
                 "width":0,
                 "x":656,
                 "y":704
                }, 
                {
                 "height":0,
                 "id":952,
                 "name":"",
                 "polyline":[
                        {
                         "x":0,
                         "y":0
                        }, 
                        {
                         "x":-8,
                         "y":-16
                        }, 
                        {
                         "x":-16,
                         "y":0
                        }],
                 "properties":
                    {

                    },
                 "rotation":0,
                 "type":"",
                 "visible":true,
                 "width":0,
                 "x":168,
                 "y":704
                }, 
                {
                 "gid":2147485776,
                 "height":64,
                 "id":953,
                 "name":"",
                 "properties":
                    {

                    },
                 "rotation":0,
                 "type":"",
                 "visible":true,
                 "width":32,
                 "x":120,
                 "y":616
                }],
         "opacity":1,
         "type":"objectgroup",
         "visible":true,
         "width":0,
         "x":0,
         "y":0
        }, 
        {
         "color":"#ff0000",
         "draworder":"topdown",
         "height":0,
         "name":"monsters & npcs",
         "objects":[
                {
                 "height":8,
                 "id":906,
                 "name":"",
                 "properties":
                    {
                     "vehicle":"compositerailplatform"
                    },
                 "rotation":0,
                 "type":"",
                 "visible":true,
                 "width":8,
                 "x":192,
                 "y":840
                }, 
                {
                 "height":8,
                 "id":907,
                 "name":"",
                 "properties":
                    {
                     "vehicle":"compositerailplatform"
                    },
                 "rotation":0,
                 "type":"",
                 "visible":true,
                 "width":8,
                 "x":632,
                 "y":840
                }],
         "opacity":1,
         "type":"objectgroup",
         "visible":true,
         "width":0,
         "x":0,
         "y":0
        }, 
        {
         "color":"#00ffff",
         "draworder":"topdown",
         "height":0,
         "name":"wiring - locked door",
         "objects":[],
         "opacity":1,
         "type":"objectgroup",
         "visible":true,
         "width":0,
         "x":0,
         "y":0
        }, 
        {
         "draworder":"topdown",
         "height":0,
         "name":"outside the map",
         "objects":[],
         "opacity":1,
         "type":"objectgroup",
         "visible":true,
         "width":0,
         "x":0,
         "y":0
        }, 
        {
         "draworder":"topdown",
         "height":0,
         "name":"anchors etc",
         "objects":[
                {
                 "gid":239,
                 "height":8,
                 "id":905,
                 "name":"",
                 "properties":
                    {

                    },
                 "rotation":0,
                 "type":"",
                 "visible":true,
                 "width":8,
                 "x":8,
                 "y":872
                }],
         "opacity":1,
         "type":"objectgroup",
         "visible":true,
         "width":0,
         "x":0,
         "y":0
        }, 
        {
         "draworder":"topdown",
         "height":0,
         "name":"items",
         "objects":[],
         "opacity":1,
         "type":"objectgroup",
         "visible":true,
         "width":0,
         "x":0,
         "y":0
        }],
 "nextobjectid":1006,
 "orientation":"orthogonal",
 "properties":
    {

    },
 "renderorder":"right-down",
 "tileheight":8,
 "tilesets":[
        {
         "firstgid":1,
         "source":"..\/..\/..\/tilesets\/packed\/materials.json"
        }, 
        {
         "firstgid":191,
         "source":"..\/..\/..\/tilesets\/packed\/supports.json"
        }, 
        {
         "firstgid":227,
         "source":"..\/..\/..\/tilesets\/packed\/miscellaneous.json"
        }, 
        {
         "firstgid":246,
         "source":"..\/..\/..\/tilesets\/packed\/liquids.json"
        }, 
        {
         "firstgid":274,
         "source":"..\/..\/..\/tilesets\/packed\/objects-by-race\/generic.json"
        }, 
        {
         "firstgid":1969,
         "source":"..\/..\/..\/tilesets\/packed\/objects-by-race\/ancient.json"
        }, 
        {
         "firstgid":2085,
         "source":"..\/..\/..\/tilesets\/packed\/objects-by-race\/apex.json"
        }, 
        {
         "firstgid":2451,
         "source":"..\/..\/..\/tilesets\/packed\/objects-by-race\/avian.json"
        }, 
        {
         "firstgid":2752,
         "source":"..\/..\/..\/tilesets\/packed\/objects-by-race\/floran.json"
        }, 
        {
         "firstgid":2944,
         "source":"..\/..\/..\/tilesets\/packed\/objects-by-race\/glitch.json"
        }, 
        {
         "firstgid":3168,
         "source":"..\/..\/..\/tilesets\/packed\/objects-by-race\/human.json"
        }, 
        {
         "firstgid":3438,
         "source":"..\/..\/..\/tilesets\/packed\/objects-by-race\/hylotl.json"
        }, 
        {
         "firstgid":3663,
         "source":"..\/..\/..\/tilesets\/packed\/objects-by-race\/novakid.json"
        }, 
        {
         "firstgid":3688,
         "source":"..\/..\/..\/tilesets\/packed\/objects-by-category\/crafting.json"
        }, 
        {
         "firstgid":3763,
         "source":"..\/..\/..\/tilesets\/packed\/objects-by-category\/decorative.json"
        }, 
        {
         "firstgid":5039,
         "source":"..\/..\/..\/tilesets\/packed\/objects-by-category\/door.json"
        }, 
        {
         "firstgid":5147,
         "source":"..\/..\/..\/tilesets\/packed\/objects-by-category\/farmable.json"
        }, 
        {
         "firstgid":5222,
         "source":"..\/..\/..\/tilesets\/packed\/objects-by-category\/furniture.json"
        }, 
        {
         "firstgid":5547,
         "source":"..\/..\/..\/tilesets\/packed\/objects-by-category\/light.json"
        }, 
        {
         "firstgid":5953,
         "source":"..\/..\/..\/tilesets\/packed\/objects-by-category\/other.json"
        }, 
        {
         "firstgid":6224,
         "source":"..\/..\/..\/tilesets\/packed\/objects-by-category\/pot.json"
        }, 
        {
         "firstgid":6521,
         "source":"..\/..\/..\/tilesets\/packed\/objects-by-category\/sapling.json"
        }, 
        {
         "firstgid":6522,
         "source":"..\/..\/..\/tilesets\/packed\/objects-by-category\/spawner.json"
        }, 
        {
         "firstgid":6537,
         "source":"..\/..\/..\/tilesets\/packed\/objects-by-category\/storage.json"
        }, 
        {
         "firstgid":6752,
         "source":"..\/..\/..\/tilesets\/packed\/objects-by-category\/teleporter.json"
        }, 
        {
         "firstgid":6782,
         "source":"..\/..\/..\/tilesets\/packed\/objects-by-category\/tools.json"
        }, 
        {
         "firstgid":6787,
         "source":"..\/..\/..\/tilesets\/packed\/objects-by-category\/trap.json"
        }, 
        {
         "firstgid":6989,
         "source":"..\/..\/..\/tilesets\/packed\/objects-by-category\/wire.json"
        }, 
        {
         "firstgid":7174,
         "source":"..\/..\/..\/tilesets\/packed\/objects-by-type\/container.json"
        }, 
        {
         "firstgid":7440,
         "source":"..\/..\/..\/tilesets\/packed\/objects-by-type\/farmable.json"
        }, 
        {
         "firstgid":7516,
         "source":"..\/..\/..\/tilesets\/packed\/objects-by-type\/loungeable.json"
        }, 
        {
         "firstgid":7762,
         "source":"..\/..\/..\/tilesets\/packed\/objects-by-type\/noisy.json"
        }, 
        {
         "firstgid":7803,
         "source":"..\/..\/..\/tilesets\/packed\/objects-by-type\/teleporter.json"
        }, 
        {
         "firstgid":7827,
         "source":"..\/..\/..\/tilesets\/packed\/huge-objects.json"
        }, 
        {
         "firstgid":7902,
         "source":"..\/..\/..\/tilesets\/packed\/objects-by-category\/rail.json"
        }],
 "tilewidth":8,
 "version":1,
 "width":106
}