{ "backgroundcolor":"#000000",
 "height":60,
 "layers":[
        {
         "compression":"zlib",
         "data":"eJzt00EKwzAMBVEfPUf7u\/ZY7SYQSh1kOZYEHsHsXEevIWrtEBERERGl1QqNNrKeo42s1xFevHjx4i05wosXL168JUd48eLFi7fkCC9evHjxlhzhxYsXL96SI7x4B3p977TmnZFn\/JbpzSja+740u7vnrkyv1z1zR7S3t29v95Gz0Vart+e3\/i9Vvl2v+c7x5Pe+yut9zytbaa3mjrJmm6OdM2br7\/6dy3SO+q3ns\/efMWfvQfv1ARFl\/Ak=",
         "encoding":"base64",
         "height":60,
         "name":"back",
         "opacity":0.5,
         "type":"tilelayer",
         "visible":true,
         "width":60,
         "x":0,
         "y":0
        }, 
        {
         "compression":"zlib",
         "data":"eJzt1FEKgzAMBmDvfzE9w06zJ6HIjLazod2+D\/IgBJrfaJcFAAAAAAAAAAAAgLvWon7NeqMyz+p1du0Mrwdqlrxbp6zboUbK+23mmfJG33M5a9QT5TzL20PNv\/Qp5z5n+XzWc5X32NdL7R0SzRrNH+XM2u+u5e586j1lZy1l5L6qbP+Ss9Q6a0vfiGp3MtLuWs08O3N7A\/KbOC0=",
         "encoding":"base64",
         "height":60,
         "name":"front",
         "opacity":1,
         "type":"tilelayer",
         "visible":true,
         "width":60,
         "x":0,
         "y":0
        }, 
        {
         "color":"#5555ff",
         "draworder":"topdown",
         "height":0,
         "name":"mods",
         "objects":[],
         "opacity":1,
         "type":"objectgroup",
         "visible":true,
         "width":0,
         "x":0,
         "y":0
        }, 
        {
         "color":"#ff0000",
         "draworder":"topdown",
         "height":0,
         "name":"objects",
         "objects":[
                {
                 "gid":198,
                 "height":8,
                 "id":905,
                 "name":"",
                 "properties":
                    {

                    },
                 "rotation":0,
                 "type":"",
                 "visible":true,
                 "width":8,
                 "x":128,
                 "y":352
                }, 
                {
                 "gid":3168,
                 "height":8,
                 "id":907,
                 "name":"",
                 "properties":
                    {

                    },
                 "rotation":0,
                 "type":"",
                 "visible":true,
                 "width":16,
                 "x":304,
                 "y":360
                }, 
                {
                 "height":8,
                 "id":912,
                 "name":"",
                 "properties":
                    {
                     "npc":"human",
                     "typeName":"villager"
                    },
                 "rotation":0,
                 "type":"",
                 "visible":true,
                 "width":8,
                 "x":312,
                 "y":352
                }, 
                {
                 "gid":207,
                 "height":8,
                 "id":915,
                 "name":"",
                 "properties":
                    {

                    },
                 "rotation":0,
                 "type":"",
                 "visible":true,
                 "width":8,
                 "x":96,
                 "y":88
                }, 
                {
                 "gid":207,
                 "height":8,
                 "id":916,
                 "name":"",
                 "properties":
                    {

                    },
                 "rotation":0,
                 "type":"",
                 "visible":true,
                 "width":8,
                 "x":368,
                 "y":88
                }, 
                {
                 "gid":195,
                 "height":8,
                 "id":917,
                 "name":"",
                 "properties":
                    {

                    },
                 "rotation":0,
                 "type":"",
                 "visible":true,
                 "width":8,
                 "x":96,
                 "y":88
                }, 
                {
                 "gid":195,
                 "height":8,
                 "id":918,
                 "name":"",
                 "properties":
                    {

                    },
                 "rotation":0,
                 "type":"",
                 "visible":true,
                 "width":8,
                 "x":368,
                 "y":88
                }, 
                {
                 "gid":2147485528,
                 "height":24,
                 "id":919,
                 "name":"",
                 "properties":
                    {

                    },
                 "rotation":0,
                 "type":"",
                 "visible":true,
                 "width":64,
                 "x":320,
                 "y":360
                }],
         "opacity":1,
         "type":"objectgroup",
         "visible":true,
         "width":0,
         "x":0,
         "y":0
        }, 
        {
         "color":"#ffff00",
         "draworder":"topdown",
         "height":0,
         "name":"wiring - lights & guns",
         "objects":[],
         "opacity":1,
         "type":"objectgroup",
         "visible":true,
         "width":0,
         "x":0,
         "y":0
        }, 
        {
         "color":"#ff0000",
         "draworder":"topdown",
         "height":0,
         "name":"monsters & npcs",
         "objects":[
                {
                 "height":8,
                 "id":921,
                 "name":"",
                 "properties":
                    {
                     "monster":"rex"
                    },
                 "rotation":0,
                 "type":"",
                 "visible":true,
                 "width":8,
                 "x":96,
                 "y":352
                }],
         "opacity":1,
         "type":"objectgroup",
         "visible":true,
         "width":0,
         "x":0,
         "y":0
        }, 
        {
         "color":"#00ffff",
         "draworder":"topdown",
         "height":0,
         "name":"wiring - locked door",
         "objects":[],
         "opacity":1,
         "type":"objectgroup",
         "visible":true,
         "width":0,
         "x":0,
         "y":0
        }, 
        {
         "draworder":"topdown",
         "height":0,
         "name":"outside the map",
         "objects":[],
         "opacity":1,
         "type":"objectgroup",
         "visible":true,
         "width":0,
         "x":0,
         "y":0
        }, 
        {
         "draworder":"topdown",
         "height":0,
         "name":"anchors etc",
         "objects":[
                {
                 "gid":196,
                 "height":8,
                 "id":713,
                 "name":"",
                 "properties":
                    {

                    },
                 "rotation":0,
                 "type":"",
                 "visible":true,
                 "width":8,
                 "x":368,
                 "y":392
                }, 
                {
                 "gid":196,
                 "height":8,
                 "id":714,
                 "name":"",
                 "properties":
                    {

                    },
                 "rotation":0,
                 "type":"",
                 "visible":true,
                 "width":8,
                 "x":96,
                 "y":392
                }, 
                {
                 "gid":207,
                 "height":8,
                 "id":722,
                 "name":"",
                 "properties":
                    {

                    },
                 "rotation":0,
                 "type":"",
                 "visible":true,
                 "width":8,
                 "x":392,
                 "y":360
                }, 
                {
                 "gid":207,
                 "height":8,
                 "id":723,
                 "name":"",
                 "properties":
                    {

                    },
                 "rotation":0,
                 "type":"",
                 "visible":true,
                 "width":8,
                 "x":80,
                 "y":360
                }, 
                {
                 "gid":195,
                 "height":8,
                 "id":727,
                 "name":"",
                 "properties":
                    {

                    },
                 "rotation":0,
                 "type":"",
                 "visible":true,
                 "width":8,
                 "x":392,
                 "y":360
                }, 
                {
                 "gid":195,
                 "height":8,
                 "id":731,
                 "name":"",
                 "properties":
                    {

                    },
                 "rotation":0,
                 "type":"",
                 "visible":true,
                 "width":8,
                 "x":80,
                 "y":360
                }, 
                {
                 "gid":203,
                 "height":8,
                 "id":880,
                 "name":"",
                 "properties":
                    {

                    },
                 "rotation":0,
                 "type":"",
                 "visible":true,
                 "width":8,
                 "x":72,
                 "y":360
                }, 
                {
                 "gid":203,
                 "height":8,
                 "id":881,
                 "name":"",
                 "properties":
                    {

                    },
                 "rotation":0,
                 "type":"",
                 "visible":true,
                 "width":8,
                 "x":400,
                 "y":360
                }, 
                {
                 "height":88,
                 "id":920,
                 "name":"",
                 "properties":
                    {
                     "stagehand":"objecttracker"
                    },
                 "rotation":0,
                 "type":"",
                 "visible":true,
                 "width":88,
                 "x":296,
                 "y":296
                }],
         "opacity":1,
         "type":"objectgroup",
         "visible":true,
         "width":0,
         "x":0,
         "y":0
        }, 
        {
         "draworder":"topdown",
         "height":0,
         "name":"items",
         "objects":[],
         "opacity":1,
         "type":"objectgroup",
         "visible":true,
         "width":0,
         "x":0,
         "y":0
        }],
 "nextobjectid":922,
 "orientation":"orthogonal",
 "properties":
    {

    },
 "renderorder":"right-down",
 "tileheight":8,
 "tilesets":[
        {
         "firstgid":1,
         "source":"..\/..\/..\/tilesets\/packed\/materials.json"
        }, 
        {
         "firstgid":191,
         "source":"..\/..\/..\/tilesets\/packed\/miscellaneous.json"
        }, 
        {
         "firstgid":210,
         "source":"..\/..\/..\/tilesets\/packed\/liquids.json"
        }, 
        {
         "firstgid":238,
         "source":"..\/..\/..\/tilesets\/packed\/supports.json"
        }, 
        {
         "firstgid":274,
         "source":"..\/..\/..\/tilesets\/packed\/objects-by-race\/generic.json"
        }, 
        {
         "firstgid":2010,
         "source":"..\/..\/..\/tilesets\/packed\/objects-by-race\/ancient.json"
        }, 
        {
         "firstgid":2127,
         "source":"..\/..\/..\/tilesets\/packed\/objects-by-race\/apex.json"
        }, 
        {
         "firstgid":2494,
         "source":"..\/..\/..\/tilesets\/packed\/objects-by-race\/avian.json"
        }, 
        {
         "firstgid":2797,
         "source":"..\/..\/..\/tilesets\/packed\/objects-by-race\/floran.json"
        }, 
        {
         "firstgid":2989,
         "source":"..\/..\/..\/tilesets\/packed\/objects-by-race\/glitch.json"
        }, 
        {
         "firstgid":3213,
         "source":"..\/..\/..\/tilesets\/packed\/objects-by-race\/human.json"
        }, 
        {
         "firstgid":3483,
         "source":"..\/..\/..\/tilesets\/packed\/objects-by-race\/hylotl.json"
        }, 
        {
         "firstgid":3713,
         "source":"..\/..\/..\/tilesets\/packed\/objects-by-race\/novakid.json"
        }, 
        {
         "firstgid":3738,
         "source":"..\/..\/..\/tilesets\/packed\/objects-by-category\/crafting.json"
        }, 
        {
         "firstgid":3814,
         "source":"..\/..\/..\/tilesets\/packed\/objects-by-category\/decorative.json"
        }, 
        {
         "firstgid":5113,
         "source":"..\/..\/..\/tilesets\/packed\/objects-by-category\/door.json"
        }, 
        {
         "firstgid":5221,
         "source":"..\/..\/..\/tilesets\/packed\/objects-by-category\/farmable.json"
        }, 
        {
         "firstgid":5296,
         "source":"..\/..\/..\/tilesets\/packed\/objects-by-category\/furniture.json"
        }, 
        {
         "firstgid":5622,
         "source":"..\/..\/..\/tilesets\/packed\/objects-by-category\/light.json"
        }, 
        {
         "firstgid":6029,
         "source":"..\/..\/..\/tilesets\/packed\/objects-by-category\/other.json"
        }, 
        {
         "firstgid":6324,
         "source":"..\/..\/..\/tilesets\/packed\/objects-by-category\/pot.json"
        }, 
        {
         "firstgid":6621,
         "source":"..\/..\/..\/tilesets\/packed\/objects-by-category\/sapling.json"
        }, 
        {
         "firstgid":6622,
         "source":"..\/..\/..\/tilesets\/packed\/objects-by-category\/spawner.json"
        }, 
        {
         "firstgid":6637,
         "source":"..\/..\/..\/tilesets\/packed\/objects-by-category\/storage.json"
        }, 
        {
         "firstgid":6853,
         "source":"..\/..\/..\/tilesets\/packed\/objects-by-category\/teleporter.json"
        }, 
        {
         "firstgid":6885,
         "source":"..\/..\/..\/tilesets\/packed\/objects-by-category\/tools.json"
        }, 
        {
         "firstgid":6890,
         "source":"..\/..\/..\/tilesets\/packed\/objects-by-category\/trap.json"
        }, 
        {
         "firstgid":7094,
         "source":"..\/..\/..\/tilesets\/packed\/objects-by-category\/wire.json"
        }, 
        {
         "firstgid":7279,
         "source":"..\/..\/..\/tilesets\/packed\/objects-by-type\/container.json"
        }, 
        {
         "firstgid":7548,
         "source":"..\/..\/..\/tilesets\/packed\/objects-by-type\/farmable.json"
        }, 
        {
         "firstgid":7624,
         "source":"..\/..\/..\/tilesets\/packed\/objects-by-type\/loungeable.json"
        }, 
        {
         "firstgid":7880,
         "source":"..\/..\/..\/tilesets\/packed\/objects-by-type\/noisy.json"
        }, 
        {
         "firstgid":7921,
         "source":"..\/..\/..\/tilesets\/packed\/objects-by-type\/teleporter.json"
        }, 
        {
         "firstgid":7946,
         "source":"..\/..\/..\/tilesets\/packed\/huge-objects.json"
        }],
 "tilewidth":8,
 "version":1,
 "width":60
}