{ "backgroundcolor":"#000000",
 "height":48,
 "layers":[
        {
         "compression":"zlib",
         "data":"eJzt1E0SgyAMBeCsvIRHdeM9epi667XaRZk6NiIkIQ8QZ97Gv3mfRDaidRv5y5OIas4djFZ2dF9PN7qjpxndzduM7uXpRXfyNqP7DG85L7qLtxndY3iHt2fvtEs4t3zTk3eKpCdvzHlMy94cp4Ub6dVYpeZSXq4bdejN7TjTbx\/KySzsZ+WVrg3nfTCpxaudR87LHTV4Lf6\/4a13nve9JXtO6I3Yr6Rmad99b2k0VgtvbP7Ornuur7V3f3Aduetn3qtvZ+GVmEt5r96V6+WsWq\/lPHt5c83S\/89znmPWXHMpb8pzVtZU93EdvLMYOq\/ssfXxPmdpDHl93tdK7mTVmtG9h7ectSVz6Km1tmK3dtZsLmmtze1lRZu9nRpz6nPcfUhnrj\/1fnR\/jRndY4TWN7ASv\/s=",
         "encoding":"base64",
         "height":48,
         "name":"back",
         "opacity":0.5,
         "type":"tilelayer",
         "visible":true,
         "width":60,
         "x":0,
         "y":0
        }, 
        {
         "compression":"zlib",
         "data":"eJzt1U0KwjAQBeCsegmP2qO48iQuvY1n0IIDIZSYzN9rknkwCMXY95GaphQ5y\/Pis4JRy47u6+lGd\/Q0o7t5m9G9PL3oTt5mdJ\/w2nnRXbzN6B7hDe\/M3i0burb\/ZibvVpmZvDVnOSN7e5wabpQ3Ca00vd2tvP\/2YxZv63NIOc6fN2N2Zm8tL3dvuOctd53UK30eR\/Jq\/P\/CG14LL9fMPV\/zc5a7TmKVeDnrpOtR3pHmLOhOntYVvTOaW6L5W5r3s7C29KB3wh049C6z2ofSesztO49ivK5RBzJr5jXQrGSVmtG9w2tnHcmcsk\/NoF1We1oL2uZpzYN2elopqzjzcLtyvnfF9O7JlfaOm5G7z5YPW1cF2w==",
         "encoding":"base64",
         "height":48,
         "name":"front",
         "opacity":1,
         "type":"tilelayer",
         "visible":true,
         "width":60,
         "x":0,
         "y":0
        }, 
        {
         "color":"#5555ff",
         "draworder":"topdown",
         "height":0,
         "name":"mods",
         "objects":[],
         "opacity":1,
         "type":"objectgroup",
         "visible":true,
         "width":0,
         "x":0,
         "y":0
        }, 
        {
         "color":"#ff0000",
         "draworder":"topdown",
         "height":0,
         "name":"objects",
         "objects":[
                {
                 "gid":1341,
                 "height":24,
                 "id":757,
                 "name":"",
                 "properties":
                    {

                    },
                 "rotation":0,
                 "type":"",
                 "visible":true,
                 "width":48,
                 "x":280,
                 "y":264
                }, 
                {
                 "gid":1342,
                 "height":24,
                 "id":758,
                 "name":"",
                 "properties":
                    {

                    },
                 "rotation":0,
                 "type":"",
                 "visible":true,
                 "width":16,
                 "x":152,
                 "y":264
                }, 
                {
                 "gid":2147484991,
                 "height":16,
                 "id":759,
                 "name":"",
                 "properties":
                    {

                    },
                 "rotation":0,
                 "type":"",
                 "visible":true,
                 "width":32,
                 "x":168,
                 "y":264
                }, 
                {
                 "gid":5772,
                 "height":8,
                 "id":762,
                 "name":"",
                 "properties":
                    {

                    },
                 "rotation":0,
                 "type":"",
                 "visible":true,
                 "width":8,
                 "x":184,
                 "y":248
                }, 
                {
                 "gid":5712,
                 "height":16,
                 "id":763,
                 "name":"",
                 "properties":
                    {

                    },
                 "rotation":0,
                 "type":"",
                 "visible":true,
                 "width":8,
                 "x":368,
                 "y":224
                }, 
                {
                 "gid":2955,
                 "height":40,
                 "id":766,
                 "name":"",
                 "properties":
                    {

                    },
                 "rotation":0,
                 "type":"",
                 "visible":true,
                 "width":40,
                 "x":344,
                 "y":264
                }, 
                {
                 "gid":2955,
                 "height":40,
                 "id":767,
                 "name":"",
                 "properties":
                    {

                    },
                 "rotation":0,
                 "type":"",
                 "visible":true,
                 "width":40,
                 "x":104,
                 "y":264
                }, 
                {
                 "gid":3072,
                 "height":24,
                 "id":775,
                 "name":"",
                 "properties":
                    {

                    },
                 "rotation":0,
                 "type":"",
                 "visible":true,
                 "width":40,
                 "x":256,
                 "y":208
                }, 
                {
                 "gid":2955,
                 "height":40,
                 "id":777,
                 "name":"",
                 "properties":
                    {

                    },
                 "rotation":0,
                 "type":"",
                 "visible":true,
                 "width":40,
                 "x":232,
                 "y":264
                }, 
                {
                 "gid":5712,
                 "height":16,
                 "id":778,
                 "name":"",
                 "properties":
                    {

                    },
                 "rotation":0,
                 "type":"",
                 "visible":true,
                 "width":8,
                 "x":120,
                 "y":224
                }, 
                {
                 "height":8,
                 "id":779,
                 "name":"",
                 "properties":
                    {
                     "monster":"savybirdcritter"
                    },
                 "rotation":0,
                 "type":"",
                 "visible":true,
                 "width":8,
                 "x":304,
                 "y":104
                }, 
                {
                 "gid":6603,
                 "height":8,
                 "id":780,
                 "name":"",
                 "properties":
                    {

                    },
                 "rotation":0,
                 "type":"",
                 "visible":true,
                 "width":16,
                 "x":208,
                 "y":160
                }, 
                {
                 "gid":2147491112,
                 "height":24,
                 "id":785,
                 "name":"",
                 "properties":
                    {
                     "parameters":"{\"treasurePools\":[\"basicTreasure\"]}"
                    },
                 "rotation":0,
                 "type":"",
                 "visible":true,
                 "width":32,
                 "x":304,
                 "y":208
                }, 
                {
                 "gid":2147491131,
                 "height":16,
                 "id":786,
                 "name":"",
                 "properties":
                    {
                     "parameters":"{\"treasurePools\":[\"basicTreasure\"]}"
                    },
                 "rotation":0,
                 "type":"",
                 "visible":true,
                 "width":24,
                 "x":336,
                 "y":192
                }, 
                {
                 "gid":2147491131,
                 "height":16,
                 "id":787,
                 "name":"",
                 "properties":
                    {
                     "parameters":"{\"treasurePools\":[\"basicTreasure\"]}"
                    },
                 "rotation":0,
                 "type":"",
                 "visible":true,
                 "width":24,
                 "x":336,
                 "y":208
                }, 
                {
                 "gid":5712,
                 "height":16,
                 "id":789,
                 "name":"",
                 "properties":
                    {

                    },
                 "rotation":0,
                 "type":"",
                 "visible":true,
                 "width":8,
                 "x":112,
                 "y":224
                }, 
                {
                 "height":8,
                 "id":802,
                 "name":"",
                 "properties":
                    {
                     "npc":"fenerox",
                     "typeName":"feneroxguard"
                    },
                 "rotation":0,
                 "type":"",
                 "visible":true,
                 "width":8,
                 "x":208,
                 "y":240
                }, 
                {
                 "height":8,
                 "id":803,
                 "name":"",
                 "properties":
                    {
                     "npc":"fenerox",
                     "typeName":"feneroxvillager"
                    },
                 "rotation":0,
                 "type":"",
                 "visible":true,
                 "width":8,
                 "x":312,
                 "y":232
                }],
         "opacity":1,
         "type":"objectgroup",
         "visible":true,
         "width":0,
         "x":0,
         "y":0
        }, 
        {
         "color":"#ffff00",
         "draworder":"topdown",
         "height":0,
         "name":"wiring - lights & guns",
         "objects":[],
         "opacity":1,
         "type":"objectgroup",
         "visible":true,
         "width":0,
         "x":0,
         "y":0
        }, 
        {
         "color":"#ff0000",
         "draworder":"topdown",
         "height":0,
         "name":"monsters & npcs",
         "objects":[
                {
                 "height":8,
                 "id":769,
                 "name":"",
                 "properties":
                    {
                     "monster":"savybirdcritter"
                    },
                 "rotation":0,
                 "type":"",
                 "visible":true,
                 "width":8,
                 "x":168,
                 "y":144
                }, 
                {
                 "height":8,
                 "id":772,
                 "name":"",
                 "properties":
                    {
                     "monster":"snakecritter"
                    },
                 "rotation":0,
                 "type":"",
                 "visible":true,
                 "width":8,
                 "x":264,
                 "y":200
                }],
         "opacity":1,
         "type":"objectgroup",
         "visible":true,
         "width":0,
         "x":0,
         "y":0
        }, 
        {
         "color":"#00ffff",
         "draworder":"topdown",
         "height":0,
         "name":"wiring - locked door",
         "objects":[],
         "opacity":1,
         "type":"objectgroup",
         "visible":true,
         "width":0,
         "x":0,
         "y":0
        }, 
        {
         "draworder":"topdown",
         "height":0,
         "name":"outside the map",
         "objects":[],
         "opacity":1,
         "type":"objectgroup",
         "visible":true,
         "width":0,
         "x":0,
         "y":0
        }, 
        {
         "draworder":"topdown",
         "height":0,
         "name":"anchors etc",
         "objects":[
                {
                 "gid":195,
                 "height":8,
                 "id":742,
                 "name":"",
                 "properties":
                    {

                    },
                 "rotation":0,
                 "type":"",
                 "visible":true,
                 "width":8,
                 "x":392,
                 "y":280
                }, 
                {
                 "gid":195,
                 "height":8,
                 "id":743,
                 "name":"",
                 "properties":
                    {

                    },
                 "rotation":0,
                 "type":"",
                 "visible":true,
                 "width":8,
                 "x":8,
                 "y":152
                }, 
                {
                 "gid":196,
                 "height":8,
                 "id":744,
                 "name":"",
                 "properties":
                    {

                    },
                 "rotation":0,
                 "type":"",
                 "visible":true,
                 "width":8,
                 "x":400,
                 "y":312
                }, 
                {
                 "gid":195,
                 "height":8,
                 "id":745,
                 "name":"",
                 "properties":
                    {

                    },
                 "rotation":0,
                 "type":"",
                 "visible":true,
                 "width":8,
                 "x":80,
                 "y":16
                }, 
                {
                 "gid":195,
                 "height":8,
                 "id":746,
                 "name":"",
                 "properties":
                    {

                    },
                 "rotation":0,
                 "type":"",
                 "visible":true,
                 "width":8,
                 "x":392,
                 "y":16
                }, 
                {
                 "gid":196,
                 "height":8,
                 "id":747,
                 "name":"",
                 "properties":
                    {

                    },
                 "rotation":0,
                 "type":"",
                 "visible":true,
                 "width":8,
                 "x":72,
                 "y":312
                }, 
                {
                 "gid":195,
                 "height":8,
                 "id":748,
                 "name":"",
                 "properties":
                    {

                    },
                 "rotation":0,
                 "type":"",
                 "visible":true,
                 "width":8,
                 "x":240,
                 "y":16
                }, 
                {
                 "gid":195,
                 "height":8,
                 "id":749,
                 "name":"",
                 "properties":
                    {

                    },
                 "rotation":0,
                 "type":"",
                 "visible":true,
                 "width":8,
                 "x":464,
                 "y":152
                }, 
                {
                 "gid":195,
                 "height":8,
                 "id":750,
                 "name":"",
                 "properties":
                    {

                    },
                 "rotation":0,
                 "type":"",
                 "visible":true,
                 "width":8,
                 "x":80,
                 "y":280
                }, 
                {
                 "gid":207,
                 "height":8,
                 "id":794,
                 "name":"",
                 "properties":
                    {

                    },
                 "rotation":0,
                 "type":"",
                 "visible":true,
                 "width":8,
                 "x":392,
                 "y":16
                }, 
                {
                 "gid":207,
                 "height":8,
                 "id":795,
                 "name":"",
                 "properties":
                    {

                    },
                 "rotation":0,
                 "type":"",
                 "visible":true,
                 "width":8,
                 "x":240,
                 "y":16
                }, 
                {
                 "gid":207,
                 "height":8,
                 "id":796,
                 "name":"",
                 "properties":
                    {

                    },
                 "rotation":0,
                 "type":"",
                 "visible":true,
                 "width":8,
                 "x":80,
                 "y":16
                }, 
                {
                 "gid":207,
                 "height":8,
                 "id":797,
                 "name":"",
                 "properties":
                    {

                    },
                 "rotation":0,
                 "type":"",
                 "visible":true,
                 "width":8,
                 "x":8,
                 "y":152
                }, 
                {
                 "gid":207,
                 "height":8,
                 "id":798,
                 "name":"",
                 "properties":
                    {

                    },
                 "rotation":0,
                 "type":"",
                 "visible":true,
                 "width":8,
                 "x":80,
                 "y":280
                }, 
                {
                 "gid":207,
                 "height":8,
                 "id":799,
                 "name":"",
                 "properties":
                    {

                    },
                 "rotation":0,
                 "type":"",
                 "visible":true,
                 "width":8,
                 "x":392,
                 "y":280
                }, 
                {
                 "gid":207,
                 "height":8,
                 "id":800,
                 "name":"",
                 "properties":
                    {

                    },
                 "rotation":0,
                 "type":"",
                 "visible":true,
                 "width":8,
                 "x":464,
                 "y":152
                }, 
                {
                 "height":160,
                 "id":805,
                 "name":"",
                 "properties":
                    {
                     "stagehand":"objecttracker"
                    },
                 "rotation":0,
                 "type":"",
                 "visible":true,
                 "width":272,
                 "x":120,
                 "y":120
                }],
         "opacity":1,
         "type":"objectgroup",
         "visible":true,
         "width":0,
         "x":0,
         "y":0
        }, 
        {
         "draworder":"topdown",
         "height":0,
         "name":"items",
         "objects":[],
         "opacity":1,
         "type":"objectgroup",
         "visible":true,
         "width":0,
         "x":0,
         "y":0
        }],
 "nextobjectid":806,
 "orientation":"orthogonal",
 "properties":
    {

    },
 "renderorder":"right-down",
 "tileheight":8,
 "tilesets":[
        {
         "firstgid":1,
         "source":"..\/..\/..\/..\/tilesets\/packed\/materials.json"
        }, 
        {
         "firstgid":191,
         "source":"..\/..\/..\/..\/tilesets\/packed\/miscellaneous.json"
        }, 
        {
         "firstgid":210,
         "source":"..\/..\/..\/..\/tilesets\/packed\/liquids.json"
        }, 
        {
         "firstgid":238,
         "source":"..\/..\/..\/..\/tilesets\/packed\/supports.json"
        }, 
        {
         "firstgid":274,
         "source":"..\/..\/..\/..\/tilesets\/packed\/objects-by-race\/generic.json"
        }, 
        {
         "firstgid":2026,
         "source":"..\/..\/..\/..\/tilesets\/packed\/objects-by-race\/ancient.json"
        }, 
        {
         "firstgid":2143,
         "source":"..\/..\/..\/..\/tilesets\/packed\/objects-by-race\/apex.json"
        }, 
        {
         "firstgid":2511,
         "source":"..\/..\/..\/..\/tilesets\/packed\/objects-by-race\/avian.json"
        }, 
        {
         "firstgid":2815,
         "source":"..\/..\/..\/..\/tilesets\/packed\/objects-by-race\/floran.json"
        }, 
        {
         "firstgid":3008,
         "source":"..\/..\/..\/..\/tilesets\/packed\/objects-by-race\/glitch.json"
        }, 
        {
         "firstgid":3233,
         "source":"..\/..\/..\/..\/tilesets\/packed\/objects-by-race\/human.json"
        }, 
        {
         "firstgid":3512,
         "source":"..\/..\/..\/..\/tilesets\/packed\/objects-by-race\/hylotl.json"
        }, 
        {
         "firstgid":3743,
         "source":"..\/..\/..\/..\/tilesets\/packed\/objects-by-race\/novakid.json"
        }, 
        {
         "firstgid":3769,
         "source":"..\/..\/..\/..\/tilesets\/packed\/objects-by-category\/crafting.json"
        }, 
        {
         "firstgid":3845,
         "source":"..\/..\/..\/..\/tilesets\/packed\/objects-by-category\/decorative.json"
        }, 
        {
         "firstgid":5144,
         "source":"..\/..\/..\/..\/tilesets\/packed\/objects-by-category\/door.json"
        }, 
        {
         "firstgid":5259,
         "source":"..\/..\/..\/..\/tilesets\/packed\/objects-by-category\/farmable.json"
        }, 
        {
         "firstgid":5334,
         "source":"..\/..\/..\/..\/tilesets\/packed\/objects-by-category\/furniture.json"
        }, 
        {
         "firstgid":5660,
         "source":"..\/..\/..\/..\/tilesets\/packed\/objects-by-category\/light.json"
        }, 
        {
         "firstgid":6075,
         "source":"..\/..\/..\/..\/tilesets\/packed\/objects-by-category\/other.json"
        }, 
        {
         "firstgid":6370,
         "source":"..\/..\/..\/..\/tilesets\/packed\/objects-by-category\/pot.json"
        }, 
        {
         "firstgid":6667,
         "source":"..\/..\/..\/..\/tilesets\/packed\/objects-by-category\/sapling.json"
        }, 
        {
         "firstgid":6668,
         "source":"..\/..\/..\/..\/tilesets\/packed\/objects-by-category\/spawner.json"
        }, 
        {
         "firstgid":6683,
         "source":"..\/..\/..\/..\/tilesets\/packed\/objects-by-category\/storage.json"
        }, 
        {
         "firstgid":6899,
         "source":"..\/..\/..\/..\/tilesets\/packed\/objects-by-category\/teleporter.json"
        }, 
        {
         "firstgid":6931,
         "source":"..\/..\/..\/..\/tilesets\/packed\/objects-by-category\/tools.json"
        }, 
        {
         "firstgid":6936,
         "source":"..\/..\/..\/..\/tilesets\/packed\/objects-by-category\/trap.json"
        }, 
        {
         "firstgid":7140,
         "source":"..\/..\/..\/..\/tilesets\/packed\/objects-by-category\/wire.json"
        }, 
        {
         "firstgid":7325,
         "source":"..\/..\/..\/..\/tilesets\/packed\/objects-by-type\/container.json"
        }, 
        {
         "firstgid":7594,
         "source":"..\/..\/..\/..\/tilesets\/packed\/objects-by-type\/farmable.json"
        }, 
        {
         "firstgid":7670,
         "source":"..\/..\/..\/..\/tilesets\/packed\/objects-by-type\/loungeable.json"
        }, 
        {
         "firstgid":7926,
         "source":"..\/..\/..\/..\/tilesets\/packed\/objects-by-type\/noisy.json"
        }, 
        {
         "firstgid":7967,
         "source":"..\/..\/..\/..\/tilesets\/packed\/objects-by-type\/teleporter.json"
        }, 
        {
         "firstgid":7992,
         "source":"..\/..\/..\/..\/tilesets\/packed\/huge-objects.json"
        }],
 "tilewidth":8,
 "version":1,
 "width":60
}