{ "backgroundcolor":"#000000",
 "height":60,
 "layers":[
        {
         "compression":"zlib",
         "data":"eJzt2E2OwyAMBWCONcebA8yqm4iLdde7zKaVkIXxMxibVEZ6qtQkDV\/4TZ+l\/D4zmUwmk8ncMq9SyijR9fNyfpN9xnpXv5X1LmZr78lmjeHxjuZYtI9zPoxzknvUPtXQWw8wS32WensFbdva+c7brfGOCj1H8kaYkTmpFtn68XHPAPF6uE\/07rKj6w3q5Z7BitfSf0fvihmxWnnb9WjVO2NGrXT9tfTOWrVeyUcz40V+y6uNuesvJrSO3HmjtON3pV1nzNy1P0wu4uXOQ1Lfnyd4R+1O++CoLT29iNnCO0pr7o2NS3l\/7zZu64++N3yuoc9Kmp9nxveOPk3H8qhI3tF9tF7r\/dXJ3h37yRlvYbyIB\/Xu2j+nFyvUi3p2ejXm9H6ft7eHPME7a9V4pX2G5LWcr1a8aJ\/WmHeuv6tW1Ez3khH7SSsrYm7H758Q6m2PSf\/ncF5rq3a+RqN9F+p5d1l3ume9HtZT\/FHWSHe019sd7fS2R9s87dEWT390vb3c0fXMZDKZTCaTkfIPH+qzMQ==",
         "encoding":"base64",
         "height":60,
         "name":"back",
         "opacity":0.5,
         "type":"tilelayer",
         "visible":true,
         "width":60,
         "x":0,
         "y":0
        }, 
        {
         "compression":"zlib",
         "data":"eJztmUuuwyAMRbOst85OsqO3A4bdS1WplhDyB7DNLz7SHSWkHDkQo15XEARBEAS78hZyCpLnSe49rrv6W7nu4ozN+dWRHZzTL1pXzHkl74RE4\/nNH5IVvDHXlF2H+WNQrjeTmc6Ua2KuU2De3D0zvDlfKRiSb3nPSGeNK+ct+Zb3jNrPvH05uD3cw93KldrfJGp8Lf1X8h3h7OWbLl\/fHud8rGedS+D7W9uLWfhSffE1wBd6rJb+U+vMnQOofuj\/lxZnGJM\/B\/PFam7pzJ19sH73bvQscxPPxX5vlC91BgLfnvpCoIY1vuWZwsKZG0v5atcztlakdTSrxtr6wv4lnR2xcd6+mLNFfSnv2nEe3yXOV1vf0vfqGGvZc4ysL2D1HA9fq\/rmc13FF+tBrOrr8Z5YOHPfX+BkX4lTfCFQ3xW8NdT6trCy75eW9dvLKq4A5Vy7fluY7Qpgzqv4ekH5eqWmhxlB7usV6GM451nUnkVbIv2fZoH23fHw5qLFaq3s5mvJyr7ePMkV40muOU\/xDIIgCILgfD5WJy+Q",
         "encoding":"base64",
         "height":60,
         "name":"front",
         "opacity":1,
         "type":"tilelayer",
         "visible":true,
         "width":60,
         "x":0,
         "y":0
        }, 
        {
         "color":"#5555ff",
         "draworder":"topdown",
         "height":0,
         "name":"mods",
         "objects":[],
         "opacity":1,
         "type":"objectgroup",
         "visible":true,
         "width":0,
         "x":0,
         "y":0
        }, 
        {
         "color":"#ff0000",
         "draworder":"topdown",
         "height":0,
         "name":"objects",
         "objects":[
                {
                 "gid":2147484909,
                 "height":16,
                 "id":782,
                 "name":"",
                 "properties":
                    {
                     "parameters":"{\"treasurePools\":[\"valuableTreasure\"]}"
                    },
                 "rotation":0,
                 "type":"",
                 "visible":true,
                 "width":16,
                 "x":288,
                 "y":184
                }, 
                {
                 "height":8,
                 "id":783,
                 "name":"",
                 "properties":
                    {
                     "monster":"snailcritter"
                    },
                 "rotation":0,
                 "type":"",
                 "visible":true,
                 "width":8,
                 "x":264,
                 "y":184
                }],
         "opacity":1,
         "type":"objectgroup",
         "visible":true,
         "width":0,
         "x":0,
         "y":0
        }, 
        {
         "color":"#ffff00",
         "draworder":"topdown",
         "height":0,
         "name":"wiring - lights & guns",
         "objects":[],
         "opacity":1,
         "type":"objectgroup",
         "visible":true,
         "width":0,
         "x":0,
         "y":0
        }, 
        {
         "color":"#ff0000",
         "draworder":"topdown",
         "height":0,
         "name":"monsters & npcs",
         "objects":[],
         "opacity":1,
         "type":"objectgroup",
         "visible":true,
         "width":0,
         "x":0,
         "y":0
        }, 
        {
         "color":"#00ffff",
         "draworder":"topdown",
         "height":0,
         "name":"wiring - locked door",
         "objects":[],
         "opacity":1,
         "type":"objectgroup",
         "visible":true,
         "width":0,
         "x":0,
         "y":0
        }, 
        {
         "draworder":"topdown",
         "height":0,
         "name":"outside the map",
         "objects":[],
         "opacity":1,
         "type":"objectgroup",
         "visible":true,
         "width":0,
         "x":0,
         "y":0
        }, 
        {
         "draworder":"topdown",
         "height":0,
         "name":"anchors etc",
         "objects":[
                {
                 "gid":217,
                 "height":8,
                 "id":773,
                 "name":"",
                 "properties":
                    {

                    },
                 "rotation":0,
                 "type":"",
                 "visible":true,
                 "width":8,
                 "x":72,
                 "y":144
                }, 
                {
                 "gid":217,
                 "height":8,
                 "id":774,
                 "name":"",
                 "properties":
                    {

                    },
                 "rotation":0,
                 "type":"",
                 "visible":true,
                 "width":8,
                 "x":408,
                 "y":320
                }, 
                {
                 "gid":218,
                 "height":8,
                 "id":778,
                 "name":"",
                 "properties":
                    {

                    },
                 "rotation":0,
                 "type":"",
                 "visible":true,
                 "width":8,
                 "x":136,
                 "y":96
                }, 
                {
                 "gid":218,
                 "height":8,
                 "id":779,
                 "name":"",
                 "properties":
                    {

                    },
                 "rotation":0,
                 "type":"",
                 "visible":true,
                 "width":8,
                 "x":56,
                 "y":216
                }, 
                {
                 "gid":218,
                 "height":8,
                 "id":780,
                 "name":"",
                 "properties":
                    {

                    },
                 "rotation":0,
                 "type":"",
                 "visible":true,
                 "width":8,
                 "x":424,
                 "y":232
                }, 
                {
                 "gid":218,
                 "height":8,
                 "id":781,
                 "name":"",
                 "properties":
                    {

                    },
                 "rotation":0,
                 "type":"",
                 "visible":true,
                 "width":8,
                 "x":352,
                 "y":384
                }],
         "opacity":1,
         "type":"objectgroup",
         "visible":true,
         "width":0,
         "x":0,
         "y":0
        }, 
        {
         "draworder":"topdown",
         "height":0,
         "name":"items",
         "objects":[],
         "opacity":1,
         "type":"objectgroup",
         "visible":true,
         "width":0,
         "x":0,
         "y":0
        }],
 "nextobjectid":784,
 "orientation":"orthogonal",
 "properties":
    {

    },
 "renderorder":"right-down",
 "tileheight":8,
 "tilesets":[
        {
         "firstgid":1,
         "source":"..\/..\/..\/..\/tilesets\/packed\/materials.json"
        }, 
        {
         "firstgid":179,
         "source":"..\/..\/..\/..\/tilesets\/packed\/supports.json"
        }, 
        {
         "firstgid":213,
         "source":"..\/..\/..\/..\/tilesets\/packed\/miscellaneous.json"
        }, 
        {
         "firstgid":231,
         "source":"..\/..\/..\/..\/tilesets\/packed\/liquids.json"
        }, 
        {
         "firstgid":257,
         "source":"..\/..\/..\/..\/tilesets\/packed\/objects-by-race\/generic.json"
        }, 
        {
         "firstgid":1556,
         "source":"..\/..\/..\/..\/tilesets\/packed\/objects-by-race\/ancient.json"
        }, 
        {
         "firstgid":1659,
         "source":"..\/..\/..\/..\/tilesets\/packed\/objects-by-race\/apex.json"
        }, 
        {
         "firstgid":1996,
         "source":"..\/..\/..\/..\/tilesets\/packed\/objects-by-race\/avian.json"
        }, 
        {
         "firstgid":2273,
         "source":"..\/..\/..\/..\/tilesets\/packed\/objects-by-race\/floran.json"
        }, 
        {
         "firstgid":2444,
         "source":"..\/..\/..\/..\/tilesets\/packed\/objects-by-race\/glitch.json"
        }, 
        {
         "firstgid":2636,
         "source":"..\/..\/..\/..\/tilesets\/packed\/objects-by-race\/human.json"
        }, 
        {
         "firstgid":2896,
         "source":"..\/..\/..\/..\/tilesets\/packed\/objects-by-race\/hylotl.json"
        }, 
        {
         "firstgid":3098,
         "source":"..\/..\/..\/..\/tilesets\/packed\/objects-by-race\/novakid.json"
        }, 
        {
         "firstgid":3123,
         "source":"..\/..\/..\/..\/tilesets\/packed\/objects-by-category\/crafting.json"
        }, 
        {
         "firstgid":3183,
         "source":"..\/..\/..\/..\/tilesets\/packed\/objects-by-category\/decorative.json"
        }, 
        {
         "firstgid":4181,
         "source":"..\/..\/..\/..\/tilesets\/packed\/objects-by-category\/door.json"
        }, 
        {
         "firstgid":4274,
         "source":"..\/..\/..\/..\/tilesets\/packed\/objects-by-category\/farmable.json"
        }, 
        {
         "firstgid":4346,
         "source":"..\/..\/..\/..\/tilesets\/packed\/objects-by-category\/furniture.json"
        }, 
        {
         "firstgid":4627,
         "source":"..\/..\/..\/..\/tilesets\/packed\/objects-by-category\/light.json"
        }, 
        {
         "firstgid":4998,
         "source":"..\/..\/..\/..\/tilesets\/packed\/objects-by-category\/other.json"
        }, 
        {
         "firstgid":5192,
         "source":"..\/..\/..\/..\/tilesets\/packed\/objects-by-category\/pot.json"
        }, 
        {
         "firstgid":5452,
         "source":"..\/..\/..\/..\/tilesets\/packed\/objects-by-category\/sapling.json"
        }, 
        {
         "firstgid":5453,
         "source":"..\/..\/..\/..\/tilesets\/packed\/objects-by-category\/spawner.json"
        }, 
        {
         "firstgid":5468,
         "source":"..\/..\/..\/..\/tilesets\/packed\/objects-by-category\/storage.json"
        }, 
        {
         "firstgid":5663,
         "source":"..\/..\/..\/..\/tilesets\/packed\/objects-by-category\/teleporter.json"
        }, 
        {
         "firstgid":5687,
         "source":"..\/..\/..\/..\/tilesets\/packed\/objects-by-category\/tools.json"
        }, 
        {
         "firstgid":5692,
         "source":"..\/..\/..\/..\/tilesets\/packed\/objects-by-category\/trap.json"
        }, 
        {
         "firstgid":5867,
         "source":"..\/..\/..\/..\/tilesets\/packed\/objects-by-category\/wire.json"
        }, 
        {
         "firstgid":6013,
         "source":"..\/..\/..\/..\/tilesets\/packed\/objects-by-type\/container.json"
        }, 
        {
         "firstgid":6251,
         "source":"..\/..\/..\/..\/tilesets\/packed\/objects-by-type\/farmable.json"
        }, 
        {
         "firstgid":6324,
         "source":"..\/..\/..\/..\/tilesets\/packed\/objects-by-type\/loungeable.json"
        }, 
        {
         "firstgid":6535,
         "source":"..\/..\/..\/..\/tilesets\/packed\/objects-by-type\/noisy.json"
        }, 
        {
         "firstgid":6576,
         "source":"..\/..\/..\/..\/tilesets\/packed\/objects-by-type\/teleporter.json"
        }, 
        {
         "firstgid":6599,
         "source":"..\/..\/..\/..\/tilesets\/packed\/huge-objects.json"
        }],
 "tilewidth":8,
 "version":1,
 "width":60
}